pyspark_utils/__init__.py
pyspark_utils/utils.py
ai_helpers_pyspark_utils-0.1.0a4.dist-info/METADATA
ai_helpers_pyspark_utils-0.1.0a4.dist-info/WHEEL
ai_helpers_pyspark_utils-0.1.0a4.dist-info/RECORD
