Metadata-Version: 2.1
Name: ai-helpers-pyspark-utils
Version: 0.1.0a4
Summary: Common pyspark utils
Home-page: https://github.com/ai-helpers/pyspark-utils
Keywords: machine-learning,pyspark,utils
Author: Corentin Vasseur
Author-email: vasseur.corentin@gmail.com
Requires-Python: >=3.9,<3.11
Classifier: Programming Language :: Python :: 3
Classifier: Programming Language :: Python :: 3.9
Classifier: Programming Language :: Python :: 3.10
Classifier: Topic :: Software Development :: Libraries :: Python Modules
Requires-Dist: pandas (>=2.2.2,<3.0.0)
Requires-Dist: pyspark (>=3.5.1,<4.0.0)
Requires-Dist: typing-extensions (>=4.10.0,<5.0.0)
Project-URL: Documentation, https://ai-helpers.github.io/pyspark-utils/
Project-URL: Repository, https://github.com/ai-helpers/pyspark-utils
